lovelaice/__init__.py
lovelaice/cli.py
lovelaice/config.py
lovelaice/core.py
lovelaice/security.py
lovelaice/template.py
lovelaice/tools/__init__.py
lovelaice/tools/filesystem.py
lovelaice-0.6.0.dist-info/METADATA
lovelaice-0.6.0.dist-info/WHEEL
lovelaice-0.6.0.dist-info/entry_points.txt
lovelaice-0.6.0.dist-info/licenses/LICENSE
lovelaice-0.6.0.dist-info/RECORD
