Metadata-Version: 2.4
Name: lovelaice
Version: 0.6.0
Summary: An open-source, extensible AI agent for your terminal.
Author-email: Alejandro Piad <apiad@apiad.net>
License-File: LICENSE
Requires-Python: >=3.13
Requires-Dist: lingo-ai==1.0rc3
Requires-Dist: purely>=0.4.2
Requires-Dist: python-dotenv>=1.2.1
Requires-Dist: rich>=14.2.0
Requires-Dist: typer>=0.21.1
